rtpy/__init__.py
rtpy/artifacts_and_storage.py
rtpy/builds.py
rtpy/import_and_export.py
rtpy/plugins.py
rtpy/repositories.py
rtpy/rtpy.py
rtpy/searches.py
rtpy/security.py
rtpy/system_and_configuration.py
rtpy/tools.py
rtpy/xray.py
rtpy-1.4.9.dist-info/LICENSE.md
rtpy-1.4.9.dist-info/WHEEL
rtpy-1.4.9.dist-info/METADATA
rtpy-1.4.9.dist-info/RECORD
